dataverse/__init__.py
dataverse/api/__init__.py
dataverse/api/cli.py
dataverse/api/emr.py
dataverse/config/__init__.py
dataverse/config/interface.py
dataverse/etl/__init__.py
dataverse/etl/pipeline.py
dataverse/etl/registry.py
dataverse/etl/__sample/__init__.py
dataverse/etl/__sample/ducky.py
dataverse/etl/__sample/github.py
dataverse/etl/bias/__init__.py
dataverse/etl/cleaning/__init__.py
dataverse/etl/cleaning/accent.py
dataverse/etl/cleaning/char.py
dataverse/etl/cleaning/document.py
dataverse/etl/cleaning/html.py
dataverse/etl/cleaning/korean.py
dataverse/etl/cleaning/length.py
dataverse/etl/cleaning/number.py
dataverse/etl/cleaning/table.py
dataverse/etl/cleaning/unicode.py
dataverse/etl/data_ingestion/__init__.py
dataverse/etl/data_ingestion/arrow.py
dataverse/etl/data_ingestion/common_crawl.py
dataverse/etl/data_ingestion/csv.py
dataverse/etl/data_ingestion/cultura_x.py
dataverse/etl/data_ingestion/huggingface.py
dataverse/etl/data_ingestion/parquet.py
dataverse/etl/data_ingestion/red_pajama.py
dataverse/etl/data_ingestion/slim_pajama.py
dataverse/etl/data_ingestion/test.py
dataverse/etl/data_load/__init__.py
dataverse/etl/data_load/aws.py
dataverse/etl/data_load/huggingface.py
dataverse/etl/data_load/parquet.py
dataverse/etl/decontamination/__init__.py
dataverse/etl/deduplication/__init__.py
dataverse/etl/deduplication/common_crawl.py
dataverse/etl/deduplication/exact.py
dataverse/etl/deduplication/minhash.py
dataverse/etl/deduplication/polyglot.py
dataverse/etl/pii/__init__.py
dataverse/etl/pii/card.py
dataverse/etl/pii/nin.py
dataverse/etl/quality/__init__.py
dataverse/etl/quality/language.py
dataverse/etl/toxicity/__init__.py
dataverse/etl/utils/__init__.py
dataverse/etl/utils/log.py
dataverse/etl/utils/sampling.py
dataverse/etl/utils/statistics.py
dataverse/lab/__init__.py
dataverse/utils/__init__.py
dataverse/utils/analyze/__init__.py
dataverse/utils/analyze/pip.py
dataverse/utils/analyze/python.py
dataverse/utils/api/__init__.py
yvestest-0.1.3.dist-info/LICENSE
yvestest-0.1.3.dist-info/METADATA
yvestest-0.1.3.dist-info/WHEEL
yvestest-0.1.3.dist-info/entry_points.txt
yvestest-0.1.3.dist-info/top_level.txt
yvestest-0.1.3.dist-info/RECORD
