Metadata-Version: 2.1
Name: yvestest
Version: 0.1.3
Summary: An open-source simplifies ETL workflow with Python based on Spark
Author: Dataverse Team
Author-email: 77601251@daum.net
License: MIT
Requires-Python: >=3.10, <=3.11
License-File: LICENSE
Requires-Dist: aiohttp ==3.9.3
Requires-Dist: aiosignal ==1.3.1
Requires-Dist: antlr4-python3-runtime ==4.9.3
Requires-Dist: attrs ==23.2.0
Requires-Dist: boto3 ==1.34.36
Requires-Dist: certifi ==2024.2.2
Requires-Dist: cfgv ==3.4.0
Requires-Dist: charset-normalizer ==3.3.2
Requires-Dist: colorama ==0.4.4
Requires-Dist: courlan ==1.0.0
Requires-Dist: datasets ==2.16.1
Requires-Dist: dateparser ==1.2.0
Requires-Dist: Faker ==23.0.0
Requires-Dist: fasttext-wheel ==0.9.2
Requires-Dist: fsspec ==2023.10.0
Requires-Dist: html2text
Requires-Dist: ipykernel >=6.29.1
Requires-Dist: ipython >=8.21.0
Requires-Dist: numpy ==1.26.4
Requires-Dist: omegaconf ==2.3.0
Requires-Dist: pandas ==2.2.0
Requires-Dist: py4j ==0.10.9.7
Requires-Dist: pyarrow ==15.0.0
Requires-Dist: pyarrow-hotfix ==0.6
Requires-Dist: pyspark ==3.5.0
Requires-Dist: pytz ==2024.1
Requires-Dist: regex ==2023.12.25
Requires-Dist: requests ==2.31.0
Requires-Dist: scipy ==1.12.0
Requires-Dist: tqdm ==4.66.1
Requires-Dist: trafilatura ==1.7.0
Provides-Extra: all
Requires-Dist: awscli ==1.32.36 ; extra == 'all'
Requires-Dist: black ==22.12.0 ; extra == 'all'
Provides-Extra: aws
Requires-Dist: awscli ==1.32.36 ; extra == 'aws'
Requires-Dist: botocore ==1.34.36 ; extra == 'aws'
Requires-Dist: rsa ==4.7.2 ; extra == 'aws'
Requires-Dist: s3transfer ==0.10.0 ; extra == 'aws'
Provides-Extra: dev
Requires-Dist: black ==22.12.0 ; extra == 'dev'
Requires-Dist: isort >=5.10.1 ; extra == 'dev'
Requires-Dist: flake8 >=4.0.1 ; extra == 'dev'
Requires-Dist: pytest >=7.4.4 ; extra == 'dev'
Requires-Dist: pre-commit ==3.6.0 ; extra == 'dev'
